gpt_guard/__init__.py
gpt_guard/extract_sensitive_data.py
gpt_guard/re_append_sensitive_data.py
gpt_guard-1.0.1.dist-info/LICENSE
gpt_guard-1.0.1.dist-info/METADATA
gpt_guard-1.0.1.dist-info/WHEEL
gpt_guard-1.0.1.dist-info/top_level.txt
gpt_guard-1.0.1.dist-info/RECORD
