Metadata-Version: 2.1
Name: gpt-guard
Version: 1.0.1
Summary: A lightweight library to sanitize data provided to AI tools
Home-page: https://github.com/Deploying-Securely/GPT-Guard
Author: Walter Haydock
Author-email: walter@deploy-securely.com
License: UNKNOWN
Platform: UNKNOWN
Classifier: License :: OSI Approved :: Apache Software License
